codeevals/__init__.py
codeevals/core.py
codeevals/main.py
codeevals/inputs/__init__.py
codeevals/inputs/llm_input.py
codeevals/metrics/__init__.py
codeevals/metrics/base_metrics.py
codeevals/metrics/logic_relevancy.py
codeevals/metrics/syntax_relevancy.py
codeevals/models/__init__.py
codeevals/models/anthropic_model.py
codeevals/models/base_model.py
codeevals/models/custom_model.py
codeevals/models/groq_model.py
codeevals/models/ollama_model.py
codeevals/models/openai_model.py
codeevals/results/__init__.py
codeevals/results/base_result.py
codeevals/results/code_relevancy_result.py
codeevals/results/evaluation_result.py
codeevals/results/syntax_relevancy_result.py
codeevals/templates/__init__.py
codeevals/templates/code_relevancy_template.py
codeevals/templates/syntax_relevancy_template.py
codeevals-0.0.2.dist-info/METADATA
codeevals-0.0.2.dist-info/WHEEL
codeevals-0.0.2.dist-info/licenses/LICENSE
codeevals-0.0.2.dist-info/RECORD
