Metadata-Version: 2.4
Name: codeevals
Version: 0.0.2
Summary: A Python package for code evaluation
Project-URL: Homepage, https://github.com/pavanjava/CodeEvals
Project-URL: Bug Tracker, https://github.com/pavanjava/CodeEvals/issues
Author-email: Your Name <your.email@example.com>
License:                                  Apache License
License-File: LICENSE
Classifier: License :: OSI Approved :: MIT License
Classifier: Operating System :: OS Independent
Classifier: Programming Language :: Python :: 3
Classifier: Programming Language :: Python :: 3.8
Classifier: Programming Language :: Python :: 3.9
Classifier: Programming Language :: Python :: 3.10
Classifier: Programming Language :: Python :: 3.11
Requires-Python: >=3.8
Requires-Dist: anthropic
Requires-Dist: click>=8.0.0
Requires-Dist: ollama
Requires-Dist: openai
Requires-Dist: rich>=12.0.0
